{
  "parent": "minecraft:recipes/root",
  "rewards": {
    "recipes": [
      "strata:rock_types/sedimentary_rocks/stonecutting/block/stairs/argillite_brick_stairs_stone_stonecutting"
    ]
  },
  "criteria": {
    "has_argillite": {
      "trigger": "minecraft:inventory_changed",
      "conditions": {
        "items": [
          {
            "item": "strata:argillite"
          }
        ]
      }
    },
    "has_the_recipe": {
      "trigger": "minecraft:recipe_unlocked",
      "conditions": {
        "recipe": "strata:argillite_brick_stairs_stone_stonecutting"
      }
    }
  },
  "requirements": [
    [
      "has_argillite_bricks",
      "has_the_recipe"
    ]
  ]
}